{
  "builtInLibrariesFolders": "C:\\Program Files\\Arduino\\libraries",
  "customBuildProperties": "build.warn_data_percentage=75,runtime.tools.avrdude.path=C:\\Program Files\\Arduino\\hardware\\tools\\avr,runtime.tools.avr-gcc.path=C:\\Program Files\\Arduino\\hardware\\tools\\avr,runtime.tools.arduinoOTA.path=C:\\Program Files\\Arduino\\hardware\\tools\\avr",
  "fqbn": "arduino:avr:uno",
  "hardwareFolders": "C:\\Program Files\\Arduino\\hardware",
  "otherLibrariesFolders": "C:\\Users\\SID\\Documents\\Arduino\\libraries",
  "runtime.ide.version": "10805",
  "sketchLocation": "E:\\SCOE\\Project (Sem-7)\\Updated (12June)\\Sample\\Sample\\Sample.ino",
  "toolsFolders": "C:\\Program Files\\Arduino\\tools-builder,C:\\Program Files\\Arduino\\hardware\\tools\\avr"
}